{
  "project_info": {
    "project_number": "438868176728",
    "firebase_url": "https://krissapp.firebaseio.com",
    "project_id": "krissapp",
    "storage_bucket": "krissapp.appspot.com"
  },
  "client": [
    {
      "client_info": {
        "mobilesdk_app_id": "1:438868176728:android:5a5d022192c86e049aff2d",
        "android_client_info": {
          "package_name": "com.fitness_master"
        }
      },
      "oauth_client": [
        {
          "client_id": "438868176728-q9kd2ns0hfcj44ko58slbgsnaf94r0n1.apps.googleusercontent.com",
          "client_type": 3
        }
      ],
      "api_key": [
        {
          "current_key": "AIzaSyAEqI97qxpDUPhKEAQ00pQjb88W7KQk-o0"
        }
      ],
      "services": {
        "appinvite_service": {
          "other_platform_oauth_client": [
            {
              "client_id": "438868176728-q9kd2ns0hfcj44ko58slbgsnaf94r0n1.apps.googleusercontent.com",
              "client_type": 3
            },
            {
              "client_id": "438868176728-bfdsevq53bp8qmocn02mo1vnjo9eb9lu.apps.googleusercontent.com",
              "client_type": 2,
              "ios_info": {
                "bundle_id": "org.reactjs.native.example.rnpush16"
              }
            }
          ]
        }
      }
    },
    {
      "client_info": {
        "mobilesdk_app_id": "1:438868176728:android:10d839a1304aac4c9aff2d",
        "android_client_info": {
          "package_name": "com.krissio"
        }
      },
      "oauth_client": [
        {
          "client_id": "438868176728-q9kd2ns0hfcj44ko58slbgsnaf94r0n1.apps.googleusercontent.com",
          "client_type": 3
        }
      ],
      "api_key": [
        {
          "current_key": "AIzaSyAEqI97qxpDUPhKEAQ00pQjb88W7KQk-o0"
        }
      ],
      "services": {
        "appinvite_service": {
          "other_platform_oauth_client": [
            {
              "client_id": "438868176728-q9kd2ns0hfcj44ko58slbgsnaf94r0n1.apps.googleusercontent.com",
              "client_type": 3
            },
            {
              "client_id": "438868176728-bfdsevq53bp8qmocn02mo1vnjo9eb9lu.apps.googleusercontent.com",
              "client_type": 2,
              "ios_info": {
                "bundle_id": "org.reactjs.native.example.rnpush16"
              }
            }
          ]
        }
      }
    },
    {
      "client_info": {
        "mobilesdk_app_id": "1:438868176728:android:00d47c7ae80185839aff2d",
        "android_client_info": {
          "package_name": "com.krisspro"
        }
      },
      "oauth_client": [
        {
          "client_id": "438868176728-q9kd2ns0hfcj44ko58slbgsnaf94r0n1.apps.googleusercontent.com",
          "client_type": 3
        }
      ],
      "api_key": [
        {
          "current_key": "AIzaSyAEqI97qxpDUPhKEAQ00pQjb88W7KQk-o0"
        }
      ],
      "services": {
        "appinvite_service": {
          "other_platform_oauth_client": [
            {
              "client_id": "438868176728-q9kd2ns0hfcj44ko58slbgsnaf94r0n1.apps.googleusercontent.com",
              "client_type": 3
            },
            {
              "client_id": "438868176728-bfdsevq53bp8qmocn02mo1vnjo9eb9lu.apps.googleusercontent.com",
              "client_type": 2,
              "ios_info": {
                "bundle_id": "org.reactjs.native.example.rnpush16"
              }
            }
          ]
        }
      }
    },
    {
      "client_info": {
        "mobilesdk_app_id": "1:438868176728:android:47a9d0f5a813f5dc9aff2d",
        "android_client_info": {
          "package_name": "com.rnpush16"
        }
      },
      "oauth_client": [
        {
          "client_id": "438868176728-q9kd2ns0hfcj44ko58slbgsnaf94r0n1.apps.googleusercontent.com",
          "client_type": 3
        }
      ],
      "api_key": [
        {
          "current_key": "AIzaSyAEqI97qxpDUPhKEAQ00pQjb88W7KQk-o0"
        }
      ],
      "services": {
        "appinvite_service": {
          "other_platform_oauth_client": [
            {
              "client_id": "438868176728-q9kd2ns0hfcj44ko58slbgsnaf94r0n1.apps.googleusercontent.com",
              "client_type": 3
            },
            {
              "client_id": "438868176728-bfdsevq53bp8qmocn02mo1vnjo9eb9lu.apps.googleusercontent.com",
              "client_type": 2,
              "ios_info": {
                "bundle_id": "org.reactjs.native.example.rnpush16"
              }
            }
          ]
        }
      }
    }
  ],
  "configuration_version": "1"
}